markdowntest/__init__.py
markdowntest/decorators.py
markdowntest/testrunner.py
markdowntest-0.0.5.dist-info/licenses/LICENSE
markdowntest-0.0.5.dist-info/METADATA
markdowntest-0.0.5.dist-info/WHEEL
markdowntest-0.0.5.dist-info/top_level.txt
markdowntest-0.0.5.dist-info/RECORD
