Metadata-Version: 2.4
Name: markdowntest
Version: 0.0.5
Summary: markdowntest: A unit test runner that renders a markdown file.
Author-email: Leon Johnson <leonjohn@iu.edu>
License-Expression: MIT
Project-URL: Homepage, https://github.com/leontoddjohnson/markdowntest
Project-URL: Issues, https://github.com/leontoddjohnson/markdowntest/issues
Keywords: autograder,higher ed,coding exercises,python education
Classifier: Development Status :: 3 - Alpha
Classifier: Programming Language :: Python :: 3
Classifier: Operating System :: OS Independent
Classifier: Intended Audience :: Education
Requires-Python: >=3.11
License-File: LICENSE
Dynamic: license-file
